tvdb_api_client/__init__.py
tvdb_api_client/client.py
tvdb_api_client/constants.py
tvdb_api_client/lib/__init__.py
tvdb_api_client/lib/type_defs.py
tvdb_api_client/models.py
tvdb_api_client/py.typed
tvdb_api_client/utils.py
tvdb_api_client-0.7.0.dist-info/LICENSE.md
tvdb_api_client-0.7.0.dist-info/METADATA
tvdb_api_client-0.7.0.dist-info/WHEEL
tvdb_api_client-0.7.0.dist-info/RECORD
