Metadata-Version: 2.3
Name: tvdb-api-client
Version: 0.7.0
Summary: A python client for TVDB rest API
Home-page: https://tvdb-api-client.readthedocs.io/en/stable/
License: BSD-3-Clause
Keywords: imdb,tv series,tvdb
Author: Stephanos Kuma
Author-email: "Stephanos Kuma" <stephanos@kuma.ai>
Requires-Python: >=3.9
Classifier: Development Status :: 4 - Beta
Classifier: Intended Audience :: Developers
Classifier: License :: OSI Approved :: BSD License
Classifier: Operating System :: OS Independent
Classifier: Programming Language :: Python :: 3 :: Only
Requires-Dist: dj-settings (~=6.0)
Requires-Dist: pathurl (~=0.7)
Requires-Dist: pyutilkit (~=0.10)
Requires-Dist: requests (~=2.0)
Project-URL: Documentation, https://tvdb-api-client.readthedocs.io/en/stable/
Project-URL: Repository, https://github.com/spapanik/tvdb_api_client
